django_getenv-1.3.2.dist-info/DESCRIPTION.rst
django_getenv-1.3.2.dist-info/METADATA
django_getenv-1.3.2.dist-info/RECORD
django_getenv-1.3.2.dist-info/WHEEL
django_getenv-1.3.2.dist-info/metadata.json
django_getenv-1.3.2.dist-info/top_level.txt
getenv/__init__.py
getenv/env.py
getenv/templatetags/__init__.py
getenv/templatetags/getenv.py
