Metadata-Version: 1.1
Name: django-getenv
Version: 1.3.2
Summary: Read settings from environment variables.
Home-page: http://github.com/schwuk/django-getenv
Author: David Murphy
Author-email: dave@schwuk.com
License: BSD
Keywords: django-getenv
Platform: UNKNOWN
Classifier: Development Status :: 5 - Production/Stable
Classifier: Intended Audience :: Developers
Classifier: License :: OSI Approved :: BSD License
Classifier: Natural Language :: English
Classifier: Programming Language :: Python :: 2
Classifier: Programming Language :: Python :: 2.6
Classifier: Programming Language :: Python :: 2.7
Classifier: Programming Language :: Python :: 3
Classifier: Programming Language :: Python :: 3.3
